<?xml version="1.0" encoding="utf-8"?>
<annotation>
<folder>images</folder>
<filename>1995e10a-image171_1.png</filename>
<source>
<database>MyDatabase</database>
<annotation>COCO2017</annotation>
<image>flickr</image>
<flickrid>NULL</flickrid>
<annotator>1</annotator>
</source>
<owner>
<flickrid>NULL</flickrid>
<name>Label Studio</name>
</owner>
<size>
<width>669</width>
<height>440</height>
<depth>4</depth>
</size>
<segmented>0</segmented>
<object>
<name>nucleo</name>
<pose>Unspecified</pose>
<truncated>0</truncated>
<difficult>0</difficult>
<bndbox>
<xmin>246</xmin>
<ymin>139</ymin>
<xmax>309</xmax>
<ymax>201</ymax>
</bndbox>
</object>
<object>
<name>deltas</name>
<pose>Unspecified</pose>
<truncated>0</truncated>
<difficult>0</difficult>
<bndbox>
<xmin>124</xmin>
<ymin>256</ymin>
<xmax>179</xmax>
<ymax>316</ymax>
</bndbox>
</object>
<object>
<name>deltas</name>
<pose>Unspecified</pose>
<truncated>0</truncated>
<difficult>0</difficult>
<bndbox>
<xmin>354</xmin>
<ymin>270</ymin>
<xmax>407</xmax>
<ymax>327</ymax>
</bndbox>
</object>
</annotation>
