<?xml version="1.0" encoding="utf-8"?>
<annotation>
<folder>images</folder>
<filename>5c82ca00-image62_3.png</filename>
<source>
<database>MyDatabase</database>
<annotation>COCO2017</annotation>
<image>flickr</image>
<flickrid>NULL</flickrid>
<annotator>1</annotator>
</source>
<owner>
<flickrid>NULL</flickrid>
<name>Label Studio</name>
</owner>
<size>
<width>680</width>
<height>430</height>
<depth>4</depth>
</size>
<segmented>0</segmented>
<object>
<name>nucelo</name>
<pose>Unspecified</pose>
<truncated>0</truncated>
<difficult>0</difficult>
<bndbox>
<xmin>286</xmin>
<ymin>149</ymin>
<xmax>333</xmax>
<ymax>212</ymax>
</bndbox>
</object>
<object>
<name>verticilo</name>
<pose>Unspecified</pose>
<truncated>0</truncated>
<difficult>0</difficult>
<bndbox>
<xmin>205</xmin>
<ymin>299</ymin>
<xmax>239</xmax>
<ymax>333</ymax>
</bndbox>
</object>
<object>
<name>verticilo</name>
<pose>Unspecified</pose>
<truncated>0</truncated>
<difficult>0</difficult>
<bndbox>
<xmin>379</xmin>
<ymin>320</ymin>
<xmax>417</xmax>
<ymax>349</ymax>
</bndbox>
</object>
</annotation>
