<?xml version="1.0" encoding="utf-8"?>
<annotation>
<folder>images</folder>
<filename>d5e4696a-image36_1.png</filename>
<source>
<database>MyDatabase</database>
<annotation>COCO2017</annotation>
<image>flickr</image>
<flickrid>NULL</flickrid>
<annotator>1</annotator>
</source>
<owner>
<flickrid>NULL</flickrid>
<name>Label Studio</name>
</owner>
<size>
<width>674</width>
<height>410</height>
<depth>4</depth>
</size>
<segmented>0</segmented>
<object>
<name>nucelo</name>
<pose>Unspecified</pose>
<truncated>0</truncated>
<difficult>0</difficult>
<bndbox>
<xmin>410</xmin>
<ymin>133</ymin>
<xmax>447</xmax>
<ymax>172</ymax>
</bndbox>
</object>
<object>
<name>verticilo</name>
<pose>Unspecified</pose>
<truncated>0</truncated>
<difficult>0</difficult>
<bndbox>
<xmin>290</xmin>
<ymin>236</ymin>
<xmax>327</xmax>
<ymax>271</ymax>
</bndbox>
</object>
<object>
<name>verticilo</name>
<pose>Unspecified</pose>
<truncated>0</truncated>
<difficult>0</difficult>
<bndbox>
<xmin>526</xmin>
<ymin>278</ymin>
<xmax>554</xmax>
<ymax>301</ymax>
</bndbox>
</object>
</annotation>
